{
  "md5": {
    "data": ["8896108220d58f3e62e7f7fd1a5efafc"],
    "ctl": [null],
    "mod": [null],
    "result": ["c04d611819a73f5ddb80cbabf381f9de"],
    "sims": ["c62aef461b23cd8d41bb73ad84813e06"],
    "run_key": ["021f2889953490fd59b4588d5f49388b"]
  },
  "results": ["data/1001.csv", "model/1001.ctl", "model/1001.mod", "results/1001.csv", "results/1001-sims.csv", "results/1001-nm.csv", "results/1001-run-key.csv", "results/1001.pdf"],
  "date": ["Wed Mar 30 09:32:27 2022"],
  "user": ["kyleb"]
}
